postnl_api/__init__.py
postnl_api/postnl_api.py
postnl_api/test_postnl_api.py
postnl_api/items/__init__.py
postnl_api/items/letter.py
postnl_api/items/package.py
postnl_api-1.2.3.dist-info/LICENSE
postnl_api-1.2.3.dist-info/METADATA
postnl_api-1.2.3.dist-info/WHEEL
postnl_api-1.2.3.dist-info/top_level.txt
postnl_api-1.2.3.dist-info/zip-safe
postnl_api-1.2.3.dist-info/RECORD
