Metadata-Version: 2.1
Name: postnl-api
Version: 1.2.3
Summary: Python wrapper for the PostNL API, a way to track packages and letters.
Home-page: https://github.com/imicknl/python-postnl-api
Author: Mick Vleeshouwer
Author-email: mick@imick.nl
License: MIT
Platform: UNKNOWN
Requires-Dist: requests (>=2.0)
